pypptxshot/__init__.py
pypptxshot/__main__.py
pypptxshot/pypptxshot.py
PyPPTXShot-1.0.0.dist-info/LICENSE
PyPPTXShot-1.0.0.dist-info/METADATA
PyPPTXShot-1.0.0.dist-info/WHEEL
PyPPTXShot-1.0.0.dist-info/top_level.txt
PyPPTXShot-1.0.0.dist-info/RECORD
