Metadata-Version: 2.1
Name: PyPPTXShot
Version: 1.0.0
Summary: A Python Screenshotting PPTX Generator
Home-page: https://github.com/ph4xmo/pypptxshot/
Author: ph4xmo
Author-email: ph4xmo@gmail.com
License: MIT
Keywords: clicker autoclicker pptx ppt generator screenshot
Classifier: Intended Audience :: Developers
Classifier: Intended Audience :: End Users/Desktop
Classifier: Intended Audience :: Education
Classifier: License :: OSI Approved :: MIT License
Classifier: Topic :: Software Development
Classifier: Programming Language :: Python :: 3
Classifier: Programming Language :: Python :: 3.8
Requires-Python: ~=3.8.10
License-File: LICENSE
Requires-Dist: PyAutoGUI ==0.9.54
Requires-Dist: python-pptx ==0.6.21
